lms
lms.py
setup.cfg
setup.py
lms.egg-info/PKG-INFO
lms.egg-info/SOURCES.txt
lms.egg-info/dependency_links.txt
lms.egg-info/requires.txt
lms.egg-info/top_level.txt