Metadata-Version: 1.0
Name: lms
Version: 1.1.0
Summary: Squeezebox server
Home-page: https://github.com/molobrakos/lms
Author: UNKNOWN
Author-email: UNKNOWN
License: UNKNOWN
Platform: UNKNOWN
